mosaic_orchestrator/__init__.py
mosaic_orchestrator/asset.py
mosaic_orchestrator/cachable_task.py
mosaic_orchestrator/cache.py
mosaic_orchestrator/config.py
mosaic_orchestrator/execution_tracker.py
mosaic_orchestrator/hookspecs.py
mosaic_orchestrator/mosaic.py
mosaic_orchestrator/mosaic_utils.py
mosaic_orchestrator/pdk.py
mosaic_orchestrator/pdk_items.py
mosaic_orchestrator/result.py
mosaic_orchestrator/task.py
mosaic_orchestrator/tool.py
mosaic_orchestrator/tree.py
mosaic_orchestrator/utils.py
mosaic_orchestrator-0.9.0.dist-info/LICENSE
mosaic_orchestrator-0.9.0.dist-info/METADATA
mosaic_orchestrator-0.9.0.dist-info/WHEEL
mosaic_orchestrator-0.9.0.dist-info/RECORD
