Metadata-Version: 2.1
Name: mosaic-orchestrator
Version: 0.9.0
Summary: MOSAIC Orchestrator for analog design automation
Home-page: https://gitlab.com/mosaic_group/mosaic_framework/main
License: Apache-2.0
Keywords: MOSAIC,orchestrator,cmos,analog,design
Author: Infineon Technologie AG
Requires-Python: >=3.9
Classifier: License :: OSI Approved :: Apache Software License
Classifier: Programming Language :: Python :: 3
Classifier: Programming Language :: Python :: 3.9
Classifier: Programming Language :: Python :: 3.10
Classifier: Programming Language :: Python :: 3.11
Requires-Dist: pluggy (>=1.0.0,<2.0.0)
Requires-Dist: pyaml (>=21.10.1,<22.0.0)
Requires-Dist: semantic-version (>=2.10.0,<3.0.0)
Project-URL: Documentation, https://mosaic-orchestrator.readthedocs.io/en/latest/
Project-URL: Repository, https://gitlab.com/mosaic_group/mosaic_framework/main
